mu_teg_sim/__init__.py
mu_teg_sim/main.py
mu_teg_sim/cli/__init__.py
mu_teg_sim/cli/cli.py
mu_teg_sim/gui/__init__.py
mu_teg_sim/gui/input_frame.py
mu_teg_sim/gui/main_frame.py
mu_teg_sim/gui/simulation_frame.py
mu_teg_sim/gui/status_bar_frame.py
mu_teg_sim/model/__init__.py
mu_teg_sim/model/model.py
mu_teg_sim/model/model_params.py
mu_teg_sim/utils/__init__.py
mu_teg_sim/utils/tk_variables.py
mu_teg_sim-1.0.1.dist-info/licenses/LICENSE
mu_teg_sim-1.0.1.dist-info/METADATA
mu_teg_sim-1.0.1.dist-info/WHEEL
mu_teg_sim-1.0.1.dist-info/entry_points.txt
mu_teg_sim-1.0.1.dist-info/top_level.txt
mu_teg_sim-1.0.1.dist-info/RECORD
