Metadata-Version: 2.4
Name: mu-teg-sim
Version: 1.0.1
Summary: An app to simulate the device physics of micro Thermoelectric Generators
Author-email: Davide Beretta <mail.davide.beretta+github@gmail.com>
Project-URL: Homepage, https://github.com/BerriesLab/mu-teg-sim
Classifier: Programming Language :: Python :: 3
Classifier: Operating System :: OS Independent
Requires-Python: >=3.6
License-File: LICENSE
Dynamic: license-file
